<?xml version = '1.0' encoding = 'UTF-8'?>
<Diagram class="oracle.dbtools.crest.swingui.logical.DPVLogical" name="Logical" id="201E95F6-1B29-134A-4AAD-DAC1296B8B4C">
<createdBy>logonrmlocal</createdBy>
<modifiedBy>logonrmlocal</modifiedBy>
<createdTime>2023-03-18 01:59:54 UTC</createdTime>
<autoRoute>false</autoRoute>
<boxInbox>true</boxInbox>
<showLegend>false</showLegend>
<showLabels>false</showLabels>
<showRelAttributes>false</showRelAttributes>
<gridEnabled>false</gridEnabled>
<showGrid>false</showGrid>
<diagramColor>-1</diagramColor>
<display>false</display>
<notation>1</notation>
<objectViews>
<OView class="oracle.dbtools.crest.swingui.logical.TVEntity" oid="1C06945A-F6ED-E521-1E39-5E36D32FF375" otype="Entity" vid="36B3C557-5DC8-315E-3DFC-98389D4ABA19">
<hideElementsInCurrentOnly>false</hideElementsInCurrentOnly>
<bounds x="585" y="85" width="170" height="110"/>
</OView>
<OView class="oracle.dbtools.crest.swingui.logical.TVEntity" oid="C45F3BDD-FD72-6F7E-184C-A366AB66A6A0" otype="Entity" vid="4E883705-2FB6-564D-50A3-455682592626">
<hideElementsInCurrentOnly>false</hideElementsInCurrentOnly>
<bounds x="145" y="88" width="170" height="110"/>
</OView>
<OView class="oracle.dbtools.crest.swingui.logical.TVEntity" oid="D9A4A45F-FC2C-4088-751A-F1F4B440F093" otype="Entity" vid="5401575A-4403-0099-D7BA-73D441B1C4E9">
<hideElementsInCurrentOnly>false</hideElementsInCurrentOnly>
<bounds x="361" y="87" width="170" height="110"/>
</OView>
</objectViews>
</Diagram>